hashers-0.2.2.dist-info/METADATA
hashers-0.2.2.dist-info/WHEEL
hashers/__init__.py
hashers/hashers.abi3.so
hashers-0.2.2.dist-info/RECORD
