Metadata-Version: 2.1
Name: hashers
Version: 0.2.2
Summary: Password hashing library in Python using Rust backend 
Keywords: uuid hash password
Author: unrahul <rahulunair@gmail.com>
Author-Email: unrahul <rahulunair@gmail.com>
License: BSD-3-Clause
